<?xml version='1.0' encoding='utf-8'?>
<soapenv:Envelope xmlns:soapenv="http://schemas.xmlsoap.org/soap/envelope/">
  <soapenv:Body>
    <ser-root:updateUnitStatusChangeResponse xmlns:ser-root="http://cityofberkeley.info/RTS/ClientPortal/API" xmlns:xsi="http://www.w3.org/2001/XMLSchema-instance">
      <response>
        <status>FAILURE</status>
        <errorMsg>Unit status cannot be same as current status. Please select appropriate status and try again.</errorMsg>
      </response>
    </ser-root:updateUnitStatusChangeResponse>
  </soapenv:Body>
</soapenv:Envelope>